tonies_api/__init__.py
tonies_api/auth.py
tonies_api/client.py
tonies_api/const.py
tonies_api/exceptions.py
tonies_api/models.py
tonies_api/tonies.py
tonies_api-0.1.2.dist-info/licenses/LICENSE
tonies_api-0.1.2.dist-info/METADATA
tonies_api-0.1.2.dist-info/WHEEL
tonies_api-0.1.2.dist-info/top_level.txt
tonies_api-0.1.2.dist-info/RECORD
