Metadata-Version: 2.4
Name: tonies-api
Version: 0.1.2
Summary: Asynchronous Python SDK for Tonies API and MQTT WebSocket
Author-email: Raphael WALTER <contact@raphael-walter.fr>
License-Expression: Apache-2.0
Project-URL: Homepage, https://github.com/Raphzer/tonies-api
Project-URL: Issues, https://github.com/Raphzer/tonies-api/issues
Requires-Python: >=3.10
License-File: LICENSE
Requires-Dist: httpx>=0.23.0
Requires-Dist: websockets>=14.0
Requires-Dist: pydantic>=2.0.0
Requires-Dist: beautifulsoup4>=4.11.0
Requires-Dist: python-dotenv>=1.0.0
Provides-Extra: dev
Requires-Dist: flake8; extra == "dev"
Dynamic: license-file
